odoo/addons/ssi_term_condition_mixin/README.rst
odoo/addons/ssi_term_condition_mixin/__init__.py
odoo/addons/ssi_term_condition_mixin/__manifest__.py
odoo/addons/ssi_term_condition_mixin/menu.xml
odoo/addons/ssi_term_condition_mixin/i18n/ssi_term_condition_mixin.pot
odoo/addons/ssi_term_condition_mixin/models/__init__.py
odoo/addons/ssi_term_condition_mixin/models/mixin_tnc.py
odoo/addons/ssi_term_condition_mixin/models/mixin_tnc_clause.py
odoo/addons/ssi_term_condition_mixin/models/mixin_tnc_section.py
odoo/addons/ssi_term_condition_mixin/models/tnc_clause.py
odoo/addons/ssi_term_condition_mixin/models/tnc_section.py
odoo/addons/ssi_term_condition_mixin/models/tnc_template.py
odoo/addons/ssi_term_condition_mixin/models/tnc_template_clause.py
odoo/addons/ssi_term_condition_mixin/models/tnc_template_section.py
odoo/addons/ssi_term_condition_mixin/security/ir.model.access.csv
odoo/addons/ssi_term_condition_mixin/static/description/icon.png
odoo/addons/ssi_term_condition_mixin/templates/tnc_templates.xml
odoo/addons/ssi_term_condition_mixin/views/tnc_clause_views.xml
odoo/addons/ssi_term_condition_mixin/views/tnc_section_views.xml
odoo/addons/ssi_term_condition_mixin/views/tnc_template_clause_views.xml
odoo/addons/ssi_term_condition_mixin/views/tnc_template_section_views.xml
odoo/addons/ssi_term_condition_mixin/views/tnc_template_views.xml
odoo14_addon_ssi_term_condition_mixin-14.0.1.2.0.dist-info/METADATA
odoo14_addon_ssi_term_condition_mixin-14.0.1.2.0.dist-info/WHEEL
odoo14_addon_ssi_term_condition_mixin-14.0.1.2.0.dist-info/top_level.txt
odoo14_addon_ssi_term_condition_mixin-14.0.1.2.0.dist-info/RECORD
